Metadata-Version: 2.1
Name: github-webhooks-framework2
Version: 0.2.2
Summary: GitHub Webhooks Framework
Author: Karech
Author-email: Maurice Faber <morriz@idiotz.nl>
License: GPL-3.0-only
Project-URL: homepage, https://github.com/morriz/github-webhooks
Project-URL: Source Code, https://github.com/morriz/github-webhooks
Project-URL: Bug Tracker, https://github.com/morriz/github-webhooks/issues
Project-URL: Origin, https://github.com/karech/github-webhooks
Keywords: github,webhooks,fastapi
Classifier: Framework :: FastAPI
Classifier: Programming Language :: Python :: 3.11
Classifier: Typing :: Typed
Classifier: Topic :: Software Development :: Libraries :: Python Modules
Requires-Python: >=3.11
License-File: LICENSE
Requires-Dist: fastapi ==0.109.2
Requires-Dist: pydantic ==2.6.1
Provides-Extra: test
Requires-Dist: black ; extra == 'test'
Requires-Dist: build ; extra == 'test'
Requires-Dist: isort ; extra == 'test'
Requires-Dist: mypy ; extra == 'test'
Requires-Dist: pre-commit ; extra == 'test'
Requires-Dist: pylint ; extra == 'test'
Requires-Dist: pyproject-fmt ; extra == 'test'
Requires-Dist: uvicorn ; extra == 'test'
Requires-Dist: twine ; extra == 'test'
